{
  "node_modules/.pnpm/@sveltejs+kit@1.0.0-next.408_svelte@3.49.0+vite@3.0.7/node_modules/@sveltejs/kit/src/runtime/client/start.js": {
    "file": "_app/immutable/start-8c93c750.js",
    "src": "node_modules/.pnpm/@sveltejs+kit@1.0.0-next.408_svelte@3.49.0+vite@3.0.7/node_modules/@sveltejs/kit/src/runtime/client/start.js",
    "isEntry": true,
    "imports": [
      "_index-d44c3c93.js"
    ],
    "dynamicImports": [
      ".svelte-kit/generated/nodes/0.js",
      ".svelte-kit/generated/nodes/1.js",
      ".svelte-kit/generated/nodes/2.js"
    ]
  },
  "src/routes/+layout.svelte": {
    "file": "_app/immutable/components/pages/_layout.svelte-0bfda789.js",
    "src": "src/routes/+layout.svelte",
    "isEntry": true,
    "imports": [
      "_index-d44c3c93.js"
    ],
    "css": [
      "_app/immutable/assets/+layout-c7681318.css"
    ]
  },
  "node_modules/.pnpm/@sveltejs+kit@1.0.0-next.408_svelte@3.49.0+vite@3.0.7/node_modules/@sveltejs/kit/src/runtime/components/error.svelte": {
    "file": "_app/immutable/components/error.svelte-50f5de91.js",
    "src": "node_modules/.pnpm/@sveltejs+kit@1.0.0-next.408_svelte@3.49.0+vite@3.0.7/node_modules/@sveltejs/kit/src/runtime/components/error.svelte",
    "isEntry": true,
    "imports": [
      "_index-d44c3c93.js"
    ]
  },
  "src/routes/+page.svelte": {
    "file": "_app/immutable/components/pages/_page.svelte-bb3881a1.js",
    "src": "src/routes/+page.svelte",
    "isEntry": true,
    "imports": [
      "_index-d44c3c93.js"
    ],
    "css": [
      "_app/immutable/assets/+page-bfed4388.css"
    ]
  },
  "_index-d44c3c93.js": {
    "file": "_app/immutable/chunks/index-d44c3c93.js"
  },
  ".svelte-kit/generated/nodes/0.js": {
    "file": "_app/immutable/chunks/0-c9709eb9.js",
    "src": ".svelte-kit/generated/nodes/0.js",
    "isDynamicEntry": true,
    "imports": [
      "src/routes/+layout.svelte",
      "_index-d44c3c93.js"
    ]
  },
  ".svelte-kit/generated/nodes/1.js": {
    "file": "_app/immutable/chunks/1-9ed294d1.js",
    "src": ".svelte-kit/generated/nodes/1.js",
    "isDynamicEntry": true,
    "imports": [
      "node_modules/.pnpm/@sveltejs+kit@1.0.0-next.408_svelte@3.49.0+vite@3.0.7/node_modules/@sveltejs/kit/src/runtime/components/error.svelte",
      "_index-d44c3c93.js"
    ]
  },
  ".svelte-kit/generated/nodes/2.js": {
    "file": "_app/immutable/chunks/2-12b5260d.js",
    "src": ".svelte-kit/generated/nodes/2.js",
    "isDynamicEntry": true,
    "imports": [
      "src/routes/+page.svelte",
      "_index-d44c3c93.js"
    ]
  },
  "src/routes/+layout.css": {
    "file": "_app/immutable/assets/+layout-c7681318.css",
    "src": "src/routes/+layout.css"
  },
  "src/routes/+page.css": {
    "file": "_app/immutable/assets/+page-bfed4388.css",
    "src": "src/routes/+page.css"
  }
}